cli.py
creators/__init__.py
creators/project.py
creators/setup_files.py
creators/work_efforts.py
providers/__init__.py
providers/ollama.py
providers/openai.py
utils/__init__.py
utils/directory_scanner.py
utils/helpers.py
utils/thought_process.py
work_efforts/__init__.py
work_efforts/scripts/__init__.py
work_efforts/scripts/ai_work_effort_creator.py
work_efforts/scripts/new_work_effort.py
work_efforts/templates/work-effort-template.md
code_conductor-0.4.1.dist-info/LICENSE
code_conductor-0.4.1.dist-info/METADATA
code_conductor-0.4.1.dist-info/WHEEL
code_conductor-0.4.1.dist-info/entry_points.txt
code_conductor-0.4.1.dist-info/top_level.txt
code_conductor-0.4.1.dist-info/RECORD
