Metadata-Version: 2.2
Name: code-conductor
Version: 0.4.1
Summary: Code Conductor toolkit for managing AI development environments and work efforts
Home-page: https://github.com/ctavolazzi/code-conductor
Author: Code Conductor Team
Author-email: ctavolazzi@gmail.com
Classifier: Programming Language :: Python :: 3
Classifier: License :: OSI Approved :: MIT License
Classifier: Operating System :: OS Independent
Classifier: Development Status :: 3 - Alpha
Requires-Python: >=3.7
License-File: LICENSE
Requires-Dist: requests
Requires-Dist: asyncio
Dynamic: author
Dynamic: author-email
Dynamic: classifier
Dynamic: description
Dynamic: description-content-type
Dynamic: home-page
Dynamic: requires-dist
Dynamic: requires-python
Dynamic: summary
